{
"type": "FeatureCollection",
"name": "greenwich-hike",
"crs": { "type": "name", "properties": { "name": "urn:ogc:def:crs:OGC:1.3:CRS84" } },
"features": [
{ "type": "Feature", "properties": { "id": 9 }, "geometry": { "type": "Point", "coordinates": [ -0.123630289026011, 51.530046109499388 ] } },
{ "type": "Feature", "properties": { "id": 1 }, "geometry": { "type": "Point", "coordinates": [ -0.123628243982849, 51.530045350911912 ] } },
{ "type": "Feature", "properties": { "id": 2 }, "geometry": { "type": "Point", "coordinates": [ -0.09121684528304, 51.491930360833607 ] } },
{ "type": "Feature", "properties": { "id": 3 }, "geometry": { "type": "Point", "coordinates": [ -0.087802409743795, 51.506391909761014 ] } },
{ "type": "Feature", "properties": { "id": 4 }, "geometry": { "type": "Point", "coordinates": [ -0.070776457976203, 51.502032341848555 ] } },
{ "type": "Feature", "properties": { "id": 5 }, "geometry": { "type": "Point", "coordinates": [ -0.033710555113569, 51.495524098939299 ] } },
{ "type": "Feature", "properties": { "id": 6 }, "geometry": { "type": "Point", "coordinates": [ 0.016220365232576, 51.489624889034147 ] } },
{ "type": "Feature", "properties": { "id": 7 }, "geometry": { "type": "Point", "coordinates": [ 0.003320475596195, 51.502981507137051 ] } },
{ "type": "Feature", "properties": { "id": 8 }, "geometry": { "type": "Point", "coordinates": [ -0.104327502205216, 51.510920288746895 ] } }
]
}
